[{"hp":"-166","str":"[<a href=\"actor_0x000000000002a22a.html\" class=\"actor colorPriest\">Shadowcola<\/a>] <a href=\"spell_15290.html\" rel=\"spell=15290\" class=\"spell\">Vampiric Embrace<\/a> hot [<a href=\"actor_0x000000000009ee57.html\" class=\"actor colorMage\">Mariia<\/a>] 140","t":"71.218"},{"hp":"","str":"[<a href=\"actor_0x00000000000cfaaa.html\" class=\"actor colorShaman\">Ogannisian<\/a>] <a href=\"spell_25422.html\" rel=\"spell=25422\" class=\"spell\">Chain Heal<\/a> (r4) crit heal [<a href=\"actor_0x000000000009ee57.html\" class=\"actor colorMage\">Mariia<\/a>] 3234","t":"71.336"},{"hp":"","str":"[<a href=\"actor_0x000000000009ee57.html\" class=\"actor colorMage\">Mariia<\/a>] gained [Environment] <a href=\"spell_16237.html\" rel=\"spell=16237\" class=\"spell\">Ancestral Fortitude<\/a>","t":"71.342"},{"hp":"","str":"[<a href=\"actor_0x000000000002a22a.html\" class=\"actor colorPriest\">Shadowcola<\/a>] <a href=\"spell_15290.html\" rel=\"spell=15290\" class=\"spell\">Vampiric Embrace<\/a> hot [<a href=\"actor_0x000000000009ee57.html\" class=\"actor colorMage\">Mariia<\/a>] 115","t":"71.608"},{"hp":"","str":"[<a href=\"actor_0x000000000002a22a.html\" class=\"actor colorPriest\">Shadowcola<\/a>] <a href=\"spell_15290.html\" rel=\"spell=15290\" class=\"spell\">Vampiric Embrace<\/a> hot [<a href=\"actor_0x000000000009ee57.html\" class=\"actor colorMage\">Mariia<\/a>] 414","t":"72.185"},{"hp":"","str":"[<a href=\"actor_0x000000000002a22a.html\" class=\"actor colorPriest\">Shadowcola<\/a>] <a href=\"spell_15290.html\" rel=\"spell=15290\" class=\"spell\">Vampiric Embrace<\/a> hot [<a href=\"actor_0x000000000009ee57.html\" class=\"actor colorMage\">Mariia<\/a>] 140","t":"74.337"},{"hp":"","str":"[<a href=\"actor_0x000000000002a22a.html\" class=\"actor colorPriest\">Shadowcola<\/a>] <a href=\"spell_15290.html\" rel=\"spell=15290\" class=\"spell\">Vampiric Embrace<\/a> hot [<a href=\"actor_0x000000000009ee57.html\" class=\"actor colorMage\">Mariia<\/a>] 115","t":"74.571"},{"hp":"","str":"[<a href=\"actor_0x000000000009ee57.html\" class=\"actor colorMage\">Mariia<\/a>] gained [Environment] <a href=\"spell_28682.html\" rel=\"spell=28682\" class=\"spell\">Combustion<\/a>","t":"84.338"},{"hp":"","str":"[<a href=\"actor_0x000000000009ee57.html\" class=\"actor colorMage\">Mariia<\/a>] gained [Environment] <a href=\"spell_12472.html\" rel=\"spell=12472\" class=\"spell\">Icy Veins<\/a>","t":"84.562"},{"hp":"","str":"[<a href=\"actor_0x000000000009ee57.html\" class=\"actor colorMage\">Mariia<\/a>] gained [Environment] <a href=\"spell_35163.html\" rel=\"spell=35163\" class=\"spell\">Blessing of the Silver Crescent<\/a>","t":"84.846"},{"hp":"","str":"[<a href=\"actor_0x000000000009ee57.html\" class=\"actor colorMage\">Mariia<\/a>] fade [Environment] <a href=\"spell_16237.html\" rel=\"spell=16237\" class=\"spell\">Ancestral Fortitude<\/a>","t":"86.350"},{"hp":"","str":"[<a href=\"actor_0x000000000009ee57.html\" class=\"actor colorMage\">Mariia<\/a>] gained [Environment] <a href=\"spell_28682.html\" rel=\"spell=28682\" class=\"spell\">Combustion<\/a> (2)","t":"89.049"},{"hp":"","str":"[<a href=\"actor_0x000000000009ee57.html\" class=\"actor colorMage\">Mariia<\/a>] gained [Environment] <a href=\"spell_28682.html\" rel=\"spell=28682\" class=\"spell\">Combustion<\/a> (3)","t":"91.538"},{"hp":"","str":"[<a href=\"actor_0x000000000009ee57.html\" class=\"actor colorMage\">Mariia<\/a>] gained [Environment] <a href=\"spell_28682.html\" rel=\"spell=28682\" class=\"spell\">Combustion<\/a> (4)","t":"94.457"},{"hp":"","str":"[<a href=\"actor_0x000000000002a22a.html\" class=\"actor colorPriest\">Shadowcola<\/a>] <a href=\"spell_15290.html\" rel=\"spell=15290\" class=\"spell\">Vampiric Embrace<\/a> hot [<a href=\"actor_0x000000000009ee57.html\" class=\"actor colorMage\">Mariia<\/a>] 131","t":"97.348"},{"hp":"","str":"[<a href=\"actor_0x000000000002a22a.html\" class=\"actor colorPriest\">Shadowcola<\/a>] <a href=\"spell_15290.html\" rel=\"spell=15290\" class=\"spell\">Vampiric Embrace<\/a> hot [<a href=\"actor_0x000000000009ee57.html\" class=\"actor colorMage\">Mariia<\/a>] 105","t":"97.443"},{"hp":"","str":"[<a href=\"actor_0x000000000009ee57.html\" class=\"actor colorMage\">Mariia<\/a>] gained [Environment] <a href=\"spell_28682.html\" rel=\"spell=28682\" class=\"spell\">Combustion<\/a> (5)","t":"97.443"},{"hp":"","str":"[<a href=\"actor_0x000000000002a22a.html\" class=\"actor colorPriest\">Shadowcola<\/a>] <a href=\"spell_15290.html\" rel=\"spell=15290\" class=\"spell\">Vampiric Embrace<\/a> hot [<a href=\"actor_0x000000000009ee57.html\" class=\"actor colorMage\">Mariia<\/a>] 121","t":"99.720"},{"hp":"","str":"[<a href=\"actor_0x000000000009ee57.html\" class=\"actor colorMage\">Mariia<\/a>] gained [Environment] <a href=\"spell_28682.html\" rel=\"spell=28682\" class=\"spell\">Combustion<\/a> (6)","t":"100.213"},{"hp":"","str":"[<a href=\"actor_0x000000000002a22a.html\" class=\"actor colorPriest\">Shadowcola<\/a>] <a href=\"spell_15290.html\" rel=\"spell=15290\" class=\"spell\">Vampiric Embrace<\/a> hot [<a href=\"actor_0x000000000009ee57.html\" class=\"actor colorMage\">Mariia<\/a>] 121","t":"100.314"},{"hp":"","str":"[<a href=\"actor_0x000000000002a22a.html\" class=\"actor colorPriest\">Shadowcola<\/a>] <a href=\"spell_15290.html\" rel=\"spell=15290\" class=\"spell\">Vampiric Embrace<\/a> hot [<a href=\"actor_0x000000000009ee57.html\" class=\"actor colorMage\">Mariia<\/a>] 131","t":"100.421"},{"hp":"","str":"[<a href=\"actor_0x000000000002a22a.html\" class=\"actor colorPriest\">Shadowcola<\/a>] <a href=\"spell_15290.html\" rel=\"spell=15290\" class=\"spell\">Vampiric Embrace<\/a> hot [<a href=\"actor_0x000000000009ee57.html\" class=\"actor colorMage\">Mariia<\/a>] 105","t":"100.531"},{"hp":"","str":"[<a href=\"actor_0x000000000009ee57.html\" class=\"actor colorMage\">Mariia<\/a>] gained [Environment] <a href=\"spell_28682.html\" rel=\"spell=28682\" class=\"spell\">Combustion<\/a> (7)","t":"102.887"},{"hp":"","str":"[<a href=\"actor_0x000000000002a22a.html\" class=\"actor colorPriest\">Shadowcola<\/a>] <a href=\"spell_15290.html\" rel=\"spell=15290\" class=\"spell\">Vampiric Embrace<\/a> hot [<a href=\"actor_0x000000000009ee57.html\" class=\"actor colorMage\">Mariia<\/a>] 131","t":"103.370"},{"hp":"","str":"[<a href=\"actor_0x000000000002a22a.html\" class=\"actor colorPriest\">Shadowcola<\/a>] <a href=\"spell_15290.html\" rel=\"spell=15290\" class=\"spell\">Vampiric Embrace<\/a> hot [<a href=\"actor_0x000000000009ee57.html\" class=\"actor colorMage\">Mariia<\/a>] 105","t":"103.466"},{"hp":"","str":"[<a href=\"actor_0x000000000009ee57.html\" class=\"actor colorMage\">Mariia<\/a>] fade [Environment] <a href=\"spell_12472.html\" rel=\"spell=12472\" class=\"spell\">Icy Veins<\/a>","t":"104.568"},{"hp":"","str":"[<a href=\"actor_0x000000000009ee57.html\" class=\"actor colorMage\">Mariia<\/a>] fade [Environment] <a href=\"spell_35163.html\" rel=\"spell=35163\" class=\"spell\">Blessing of the Silver Crescent<\/a>","t":"104.742"},{"hp":"","str":"[<a href=\"actor_0x000000000009ee57.html\" class=\"actor colorMage\">Mariia<\/a>] fade [Environment] <a href=\"spell_28682.html\" rel=\"spell=28682\" class=\"spell\">Combustion<\/a>","t":"105.837"},{"hp":"","str":"[<a href=\"actor_0x000000000002a22a.html\" class=\"actor colorPriest\">Shadowcola<\/a>] <a href=\"spell_15290.html\" rel=\"spell=15290\" class=\"spell\">Vampiric Embrace<\/a> hot [<a href=\"actor_0x000000000009ee57.html\" class=\"actor colorMage\">Mariia<\/a>] 411","t":"105.850"},{"hp":"","str":"[<a href=\"actor_0x000000000002a22a.html\" class=\"actor colorPriest\">Shadowcola<\/a>] <a href=\"spell_15290.html\" rel=\"spell=15290\" class=\"spell\">Vampiric Embrace<\/a> hot [<a href=\"actor_0x000000000009ee57.html\" class=\"actor colorMage\">Mariia<\/a>] 131","t":"106.428"},{"hp":"","str":"[<a href=\"actor_0x000000000002a22a.html\" class=\"actor colorPriest\">Shadowcola<\/a>] <a href=\"spell_15290.html\" rel=\"spell=15290\" class=\"spell\">Vampiric Embrace<\/a> hot [<a href=\"actor_0x000000000009ee57.html\" class=\"actor colorMage\">Mariia<\/a>] 105","t":"106.554"},{"hp":"","str":"[<a href=\"actor_0x000000000002a22a.html\" class=\"actor colorPriest\">Shadowcola<\/a>] <a href=\"spell_15290.html\" rel=\"spell=15290\" class=\"spell\">Vampiric Embrace<\/a> hot [<a href=\"actor_0x000000000009ee57.html\" class=\"actor colorMage\">Mariia<\/a>] 121","t":"107.098"},{"hp":"-5048","str":"[<a href=\"actor_0xf130004990013ef3.html\" class=\"actor colorMob\">Krosh Firehand<\/a>] <a href=\"spell_33061.html\" rel=\"spell=33061\" class=\"spell\">Blast Wave<\/a> hit [<a href=\"actor_0x000000000009ee57.html\" class=\"actor colorMage\">Mariia<\/a>] 5048 (1682 resisted)","t":"107.098"},{"hp":"-5048","str":"[<a href=\"actor_0x000000000009ee57.html\" class=\"actor colorMage\">Mariia<\/a>] afflicted by [Environment] <a href=\"spell_33061.html\" rel=\"spell=33061\" class=\"spell\">Blast Wave<\/a>","t":"107.113"},{"hp":"-5048","str":"[<a href=\"actor_0x000000000009ee57.html\" class=\"actor colorMage\">Mariia<\/a>] fade [Environment] <a href=\"spell_33061.html\" rel=\"spell=33061\" class=\"spell\">Blast Wave<\/a>","t":"111.715"},{"hp":"-5048","str":"[<a href=\"actor_0x000000000009ee57.html\" class=\"actor colorMage\">Mariia<\/a>] gained [Environment] <a href=\"spell_45438.html\" rel=\"spell=45438\" class=\"spell\">Ice Block<\/a>","t":"111.715"},{"hp":"-5048","str":"[<a href=\"actor_0x000000000009ee57.html\" class=\"actor colorMage\">Mariia<\/a>] afflicted by [Environment] <a href=\"spell_41425.html\" rel=\"spell=41425\" class=\"spell\">Hypothermia<\/a>","t":"111.715"},{"hp":"-5048","str":"[<a href=\"actor_0x000000000009ee57.html\" class=\"actor colorMage\">Mariia<\/a>] fade [Environment] <a href=\"spell_45438.html\" rel=\"spell=45438\" class=\"spell\">Ice Block<\/a>","t":"113.912"},{"hp":"-5048","str":"[<a href=\"actor_0x000000000009ee57.html\" class=\"actor colorMage\">Mariia<\/a>] gained [Environment] <a href=\"spell_1953.html\" rel=\"spell=1953\" class=\"spell\">Blink<\/a>","t":"114.549"},{"hp":"-17966","str":"[<a href=\"actor_0xf130004990013ef3.html\" class=\"actor colorMob\">Krosh Firehand<\/a>] <a href=\"spell_33051.html\" rel=\"spell=33051\" class=\"spell\">Greater Fireball<\/a> hit [<a href=\"actor_0x000000000009ee57.html\" class=\"actor colorMage\">Mariia<\/a>] 12918","t":"114.714"}]