[{"hp":"","str":"[<a href=\"actor_0xf130004373042301.html\" class=\"actor colorMob\">Fiendish Imp #8<\/a>] afflicted by [Environment] <a href=\"spell_27173.html\" rel=\"spell=27173\" class=\"spell\">Consecration<\/a> (r6)","t":"55.461"},{"hp":"","str":"[<a href=\"actor_0xf130003c7c042300.html\" class=\"actor colorMob\">Magma Totem V #1<\/a>] <a href=\"spell_25550.html\" rel=\"spell=25550\" class=\"spell\">Magma Totem<\/a> [<a href=\"actor_0xf130004373042301.html\" class=\"actor colorMob\">Fiendish Imp #8<\/a>] immune","t":"56.091"},{"hp":"-94","str":"[<a href=\"actor_0x00000000000bf530.html\" class=\"actor colorPaladin\">Mograiner<\/a>] <a href=\"spell_27173.html\" rel=\"spell=27173\" class=\"spell\">Consecration<\/a> (r6) dot [<a href=\"actor_0xf130004373042301.html\" class=\"actor colorMob\">Fiendish Imp #8<\/a>] 94","t":"56.576"},{"hp":"-94","str":"[<a href=\"actor_0xf130004373042301.html\" class=\"actor colorMob\">Fiendish Imp #8<\/a>] fade [Environment] <a href=\"spell_27173.html\" rel=\"spell=27173\" class=\"spell\">Consecration<\/a> (r6)","t":"56.996"},{"hp":"-231","str":"[<a href=\"actor_0x00000000000cdd27.html\" class=\"actor colorWarrior\">Violenthia<\/a>] <a href=\"spell_25264.html\" rel=\"spell=25264\" class=\"spell\">Thunder Clap<\/a> (r7) hit [<a href=\"actor_0xf130004373042301.html\" class=\"actor colorMob\">Fiendish Imp #8<\/a>] 137","t":"57.635"},{"hp":"-231","str":"[<a href=\"actor_0xf130004373042301.html\" class=\"actor colorMob\">Fiendish Imp #8<\/a>] afflicted by [Environment] <a href=\"spell_25264.html\" rel=\"spell=25264\" class=\"spell\">Thunder Clap<\/a> (r7)","t":"57.635"},{"hp":"-231","str":"[<a href=\"actor_0xf130003c7c042300.html\" class=\"actor colorMob\">Magma Totem V #1<\/a>] <a href=\"spell_25550.html\" rel=\"spell=25550\" class=\"spell\">Magma Totem<\/a> [<a href=\"actor_0xf130004373042301.html\" class=\"actor colorMob\">Fiendish Imp #8<\/a>] immune","t":"58.131"},{"hp":"-231","str":"[<a href=\"actor_0xf130004373042301.html\" class=\"actor colorMob\">Fiendish Imp #8<\/a>] afflicted by [Environment] <a href=\"spell_27173.html\" rel=\"spell=27173\" class=\"spell\">Consecration<\/a> (r6)","t":"58.431"},{"hp":"-2380","str":"[<a href=\"actor_0x00000000000c1fc3.html\" class=\"actor colorMob\">Nubluls<\/a>] <a href=\"spell_27285.html\" rel=\"spell=27285\" class=\"spell\">Seed of Corruption<\/a> crit [<a href=\"actor_0xf130004373042301.html\" class=\"actor colorMob\">Fiendish Imp #8<\/a>] 2149","t":"58.716"},{"hp":"-2380","str":"[<a href=\"actor_0xf130004373042301.html\" class=\"actor colorMob\">Fiendish Imp #8<\/a>] afflicted by [Environment] <a href=\"spell_25203.html\" rel=\"spell=25203\" class=\"spell\">Demoralizing Shout<\/a> (r7)","t":"59.336"},{"hp":"-2474","str":"[<a href=\"actor_0x00000000000bf530.html\" class=\"actor colorPaladin\">Mograiner<\/a>] <a href=\"spell_27173.html\" rel=\"spell=27173\" class=\"spell\">Consecration<\/a> (r6) dot [<a href=\"actor_0xf130004373042301.html\" class=\"actor colorMob\">Fiendish Imp #8<\/a>] 94","t":"59.449"},{"hp":"-2474","str":"[<a href=\"actor_0xf130003c7c042300.html\" class=\"actor colorMob\">Magma Totem V #1<\/a>] <a href=\"spell_25550.html\" rel=\"spell=25550\" class=\"spell\">Magma Totem<\/a> [<a href=\"actor_0xf130004373042301.html\" class=\"actor colorMob\">Fiendish Imp #8<\/a>] immune","t":"60.101"},{"hp":"-2568","str":"[<a href=\"actor_0x00000000000bf530.html\" class=\"actor colorPaladin\">Mograiner<\/a>] <a href=\"spell_27173.html\" rel=\"spell=27173\" class=\"spell\">Consecration<\/a> (r6) dot [<a href=\"actor_0xf130004373042301.html\" class=\"actor colorMob\">Fiendish Imp #8<\/a>] 94","t":"60.484"},{"hp":"-2662","str":"[<a href=\"actor_0x00000000000bf530.html\" class=\"actor colorPaladin\">Mograiner<\/a>] <a href=\"spell_27173.html\" rel=\"spell=27173\" class=\"spell\">Consecration<\/a> (r6) dot [<a href=\"actor_0xf130004373042301.html\" class=\"actor colorMob\">Fiendish Imp #8<\/a>] 94","t":"61.628"},{"hp":"-4170","str":"[<a href=\"actor_0x00000000000c1fc3.html\" class=\"actor colorMob\">Nubluls<\/a>] <a href=\"spell_27285.html\" rel=\"spell=27285\" class=\"spell\">Seed of Corruption<\/a> hit [<a href=\"actor_0xf130004373042301.html\" class=\"actor colorMob\">Fiendish Imp #8<\/a>] 1508","t":"61.719"},{"hp":"-5757","str":"[<a href=\"actor_0x00000000000c21d1.html\" class=\"actor colorMob\">Flataan<\/a>] <a href=\"spell_27285.html\" rel=\"spell=27285\" class=\"spell\">Seed of Corruption<\/a> hit [<a href=\"actor_0xf130004373042301.html\" class=\"actor colorMob\">Fiendish Imp #8<\/a>] 1587","t":"61.722"}]